maverage/__about__.py
maverage/__init__.py
maverage/simple.py
maverage-0.0.1.dist-info/METADATA
maverage-0.0.1.dist-info/WHEEL
maverage-0.0.1.dist-info/licenses/LICENSE.txt
maverage-0.0.1.dist-info/RECORD
