Metadata-Version: 2.1
Name: maverage
Version: 0.0.1
Summary: Light implementations for using moving averages in real time.
Project-URL: Homepage, https://github.com/gunderbolt/maverage
Project-URL: Bug Tracker, https://github.com/gunderbolt/maverage/issues
Author-email: Nick Gunderson <go2nick@gmail.com>
License-Expression: MIT
License-File: LICENSE.txt
Classifier: License :: OSI Approved :: MIT License
Classifier: Operating System :: OS Independent
Classifier: Programming Language :: Python :: 3
Requires-Python: >=3.7
